odoo/addons/stock_picking_product_availability_inline/README.rst
odoo/addons/stock_picking_product_availability_inline/__init__.py
odoo/addons/stock_picking_product_availability_inline/__manifest__.py
odoo/addons/stock_picking_product_availability_inline/i18n/stock_picking_product_availability_inline.pot
odoo/addons/stock_picking_product_availability_inline/models/__init__.py
odoo/addons/stock_picking_product_availability_inline/models/product_product.py
odoo/addons/stock_picking_product_availability_inline/models/stock_picking.py
odoo/addons/stock_picking_product_availability_inline/readme/CONTRIBUTORS.rst
odoo/addons/stock_picking_product_availability_inline/readme/DESCRIPTION.rst
odoo/addons/stock_picking_product_availability_inline/readme/USAGE.rst
odoo/addons/stock_picking_product_availability_inline/static/description/icon.png
odoo/addons/stock_picking_product_availability_inline/static/description/index.html
odoo/addons/stock_picking_product_availability_inline/tests/__init__.py
odoo/addons/stock_picking_product_availability_inline/tests/test_stock_picking_product_availability_inline.py
odoo/addons/stock_picking_product_availability_inline/views/stock_move_line_views.xml
odoo/addons/stock_picking_product_availability_inline/views/stock_picking_views.xml
odoo13_addon_stock_picking_product_availability_inline-13.0.1.1.1.dist-info/METADATA
odoo13_addon_stock_picking_product_availability_inline-13.0.1.1.1.dist-info/WHEEL
odoo13_addon_stock_picking_product_availability_inline-13.0.1.1.1.dist-info/top_level.txt
odoo13_addon_stock_picking_product_availability_inline-13.0.1.1.1.dist-info/RECORD
